video_streamer-1.0.data/scripts/video_streamer.py
video_streamer-1.0.data/scripts/video_streamer_server.py
video_streamer-1.0.data/scripts/video_streamer_setter.py
vstreamer/__init__.py
vstreamer/__main__.py
vstreamer/application/VideoStreamerApplication.py
vstreamer/application/__init__.py
vstreamer/client/MainWindow.py
vstreamer/client/MainWindow.ui
vstreamer/client/__init__.py
vstreamer/client/list/DirectoryInfoView.py
vstreamer/client/list/DirectoryInfoView.ui
vstreamer/client/list/FileEntryWidget.py
vstreamer/client/list/FileEntryWidget.ui
vstreamer/client/list/PropertiesWidget.py
vstreamer/client/list/PropertiesWidget.ui
vstreamer/client/list/__init__.py
vstreamer/client/login/ConnectDialog.py
vstreamer/client/login/ConnectDialog.ui
vstreamer/client/login/LoginDialog.py
vstreamer/client/login/LoginDialog.ui
vstreamer/client/login/__init__.py
vstreamer/client/player/VideoPlayer.py
vstreamer/client/player/VideoPlayerBar.py
vstreamer/client/player/VideoPlayerBar.ui
vstreamer/client/player/__init__.py
vstreamer/directories/DirectoryCache.py
vstreamer/directories/DirectoryService.py
vstreamer/directories/__init__.py
vstreamer/resources/resources.qrc
vstreamer/resources/resources.rcc
vstreamer/resources/icons/Avatar.png
vstreamer/resources/icons/DirectoryIcon.png
vstreamer/resources/icons/FastForward.png
vstreamer/resources/icons/FastRewind.png
vstreamer/resources/icons/Fullscreen.png
vstreamer/resources/icons/Pause.png
vstreamer/resources/icons/Play.png
vstreamer/resources/icons/Stop.png
vstreamer/resources/icons/VideoFileIcon.png
vstreamer/resources/icons/VolumeDown.png
vstreamer/resources/icons/VolumeOff.png
vstreamer_server/__init__.py
vstreamer_server/__main__.py
vstreamer_server/application/VideoStreamerServerApplication.py
vstreamer_server/application/__init__.py
vstreamer_server/communication/RequestHandler.py
vstreamer_server/communication/__init__.py
vstreamer_server/config/Configuration.py
vstreamer_server/config/__init__.py
video_streamer-1.0.dist-info/LICENSE.txt
video_streamer-1.0.dist-info/METADATA
video_streamer-1.0.dist-info/WHEEL
video_streamer-1.0.dist-info/top_level.txt
video_streamer-1.0.dist-info/RECORD
