Metadata-Version: 2.1
Name: video-streamer
Version: 1.0
Summary: Client-server video streaming application
Home-page: https://github.com/artudi54/video_streamer
Author: Artur Pietrzyk, Tomasz Kolbusz
Author-email: artudi54@gmail.com, tomaszkolbusz1@gmail.com
License: UNKNOWN
Platform: UNKNOWN
Classifier: Programming Language :: Python :: 3
Classifier: License :: OSI Approved :: MIT License
Classifier: Operating System :: Microsoft :: Windows
Classifier: Operating System :: POSIX :: Linux
Requires-Dist: pycairo
Requires-Dist: PyGObject
Requires-Dist: pymediainfo
Requires-Dist: PySide2
Requires-Dist: python-vlc
